hydra_lsp/__init__.py
hydra_lsp/__main__.py
hydra_lsp/autocomplete.py
hydra_lsp/context.py
hydra_lsp/intel.py
hydra_lsp/parser.py
hydra_lsp/server.py
hydra_lsp/utils.py
hydra_lsp-0.1.3.dist-info/LICENSE
hydra_lsp-0.1.3.dist-info/METADATA
hydra_lsp-0.1.3.dist-info/WHEEL
hydra_lsp-0.1.3.dist-info/entry_points.txt
hydra_lsp-0.1.3.dist-info/RECORD
