Metadata-Version: 2.1
Name: hydra-lsp
Version: 0.1.3
Summary: Language server for Hydra YAML config files
Home-page: https://github.com/Retsediv/hydra-lsp
Keywords: ls,language-server,yaml,hydra
Author: Andrii Zhuravchak
Author-email: retsediv1@gmail.com
Requires-Python: >=3.8,<4.0
Classifier: Programming Language :: Python :: 3
Classifier: Programming Language :: Python :: 3.8
Classifier: Programming Language :: Python :: 3.9
Classifier: Programming Language :: Python :: 3.10
Classifier: Programming Language :: Python :: 3.11
Requires-Dist: importlib-metadata (>=6.8.0,<7.0.0)
Requires-Dist: intervaltree (>=3.1.0,<4.0.0)
Requires-Dist: lsprotocol (>=2023.0.0b1,<2024.0.0)
Requires-Dist: pygls (>=1.1.1,<2.0.0)
Requires-Dist: pygtrie (>=2.5.0,<3.0.0)
Requires-Dist: ruamel-yaml (>=0.17.40,<0.18.0)
